{
    "h150": {
        "name": "Flur",
        "data": 1346,
        "x": 88,
        "y": 60,
        "weights": {
            "h144": 19.0,
            "h151": 24.0
        }
    },
    "h151": {
        "name": "Flur",
        "data": 1346,
        "x": 64,
        "y": 60,
        "weights": {
            "h150": 24.0,
            "e5": 4.0,
            "h152": 38.0
        }
    },
    "h144": {
        "name": "Flur",
        "data": 1346,
        "x": 86,
        "y": 41,
        "weights": {
            "h150": 19.0,
            "h143": 12.0
        }
    },
    "h143": {
        "name": "Flur",
        "data": 1346,
        "x": 76,
        "y": 41,
        "weights": {
            "h144": 12.0,
            "e10": 3.0,
            "h142": 22.0
        }
    },
    "e5": {
        "name": "Eingang neben Mensa",
        "data": 5445,
        "x": 64,
        "y": 55,
        "weights": {
            "h151": 3.0,
            "t20": 12.0
        }
    },
    "t20": {
        "name": "Treppe",
        "data": 323,
        "x": 65,
        "y": 45,
        "weights": {
            "t19": 5.0,
            "e5": 12.0
        }
    },
    "e10": {
        "name": "Eingang D-Gebäude",
        "data": 4421,
        "x": 76,
        "y": 44,
        "weights": {
            "h145": 5.0,
            "h143": 3.0
        }
    },
    "h145": {
        "name": "Flur",
        "data": 322,
        "x": 76,
        "y": 49,
        "weights": {
            "e10": 5.0,
            "d9": 3.0,
            "h146": 2.2,
            "d001": 2.2
        }
    },
    "d9": {
        "name": "Tür",
        "data": 325,
        "x": 73,
        "y": 49,
        "weights": {
            "h147": 1.0,
            "h145": 3.0
        }
    },
    "h147": {
        "name": "Flur",
        "data": 322,
        "x": 72,
        "y": 49,
        "weights": {
            "d9": 1.0,
            "d006": 1.0,
            "d007": 1.0
        }
    },
    "d006": {
        "name": "Lager D006",
        "data": 8513,
        "x": 72,
        "y": 48,
        "weights": {
            "h147": 1.0
        }
    },
    "d007": {
        "name": "Büro D007",
        "data": 321,
        "x": 71,
        "y": 49,
        "weights": {
            "h147": 1.0
        }
    },
    "d001": {
        "name": "Verwaltung D001",
        "data": 321,
        "x": 78,
        "y": 48,
        "weights": {
            "h145": 2.2
        }
    },
    "h146": {
        "name": "Flur",
        "data": 322,
        "x": 77,
        "y": 51,
        "weights": {
            "h145": 2.2,
            "d8": 1.0,
            "t18": 1.0
        }
    },
    "t18": {
        "name": "Treppe",
        "data": 323,
        "x": 77,
        "y": 52,
        "weights": {
            "t17": 5.0,
            "h146": 1.0
        }
    },
    "d8": {
        "name": "Tür",
        "data": 325,
        "x": 78,
        "y": 51,
        "weights": {
            "h146": 1.0,
            "h148": 2.0
        }
    },
    "h148": {
        "name": "Flur",
        "data": 322,
        "x": 80,
        "y": 51,
        "weights": {
            "d8": 2.0,
            "h149": 3.0,
            "wc_21": 1.4,
            "wc_22": 1.4
        }
    },
    "wc_21": {
        "name": "Toilette D005",
        "data": 326,
        "x": 79,
        "y": 52,
        "weights": {
            "h148": 1.4
        }
    },
    "wc_22": {
        "name": "Toilette D004",
        "data": 326,
        "x": 81,
        "y": 52,
        "weights": {
            "h148": 1.4
        }
    },
    "h149": {
        "name": "Flur",
        "data": 322,
        "x": 83,
        "y": 51,
        "weights": {
            "d003": 1.0,
            "d002": 1.0,
            "h148": 3.0
        }
    },
    "d003": {
        "name": "Büro D003",
        "data": 321,
        "x": 83,
        "y": 52,
        "weights": {
            "h149": 1.0
        }
    },
    "d002": {
        "name": "Büro D002",
        "data": 321,
        "x": 83,
        "y": 50,
        "weights": {
            "h149": 1.0
        }
    },
    "h142": {
        "name": "Flur",
        "data": 1314,
        "x": 54,
        "y": 41,
        "weights": {
            "me": 3.0,
            "h141": 14.0,
            "h143": 22.0
        }
    },
    "h141": {
        "name": "Flur",
        "data": 290,
        "x": 40,
        "y": 41,
        "weights": {
            "h142": 14.0,
            "h140": 14.0,
            "mc": 3.0
        }
    },
    "m3": {
        "name": "Mensa Ausgang",
        "data": 1317,
        "x": 54,
        "y": 44,
        "weights": {
            "h142": 3.0,
            "md": 9.0
        }
    },
    "md": {
        "name": "Mensa",
        "data": 1313,
        "x": 54,
        "y": 53,
        "weights": {
            "mb": 14.0,
            "me": 9.0
        }
    },
    "mc": {
        "name": "Mensa Ausgang",
        "data": 5413,
        "x": 40,
        "y": 44,
        "weights": {
            "h141": 3.0,
            "mb": 9.0
        }
    },
    "mb": {
        "name": "Mensa",
        "data": 1313,
        "x": 40,
        "y": 53,
        "weights": {
            "md": 14.0,
            "mc": 9.0,
            "ma": 3.0
        }
    },
    "ma": {
        "name": "Mensa",
        "data": 1313,
        "x": 37,
        "y": 53,
        "weights": {
            "h155": 1.0,
            "mb": 3.0
        }
    },
    "h155": {
        "name": "Flur",
        "data": 1314,
        "x": 36,
        "y": 53,
        "weights": {
            "ma": 1.0,
            "a5": 1.0,
            "h154": 4.0
        }
    },
    "a5": {
        "name": "Kaffeeautomat",
        "data": 1319,
        "x": 36,
        "y": 54,
        "weights": {
            "h155": 1.0
        }
    },
    "h154": {
        "name": "Flur",
        "data": 1314,
        "x": 32,
        "y": 53,
        "weights": {
            "a4": 1.0,
            "h155": 4.0,
            "h153": 6.1,
            "a6": 3.2,
            "a7": 5.1,
            "a8": 8.1
        }
    },
    "a4": {
        "name": "Snackautomat",
        "data": 1319,
        "x": 32,
        "y": 54,
        "weights": {
            "h154": 1.0
        }
    },
    "a6": {
        "name": "Parkguthabenautomat",
        "data": 1319,
        "x": 31,
        "y": 50,
        "weights": {
            "h154": 3.2
        }
    },
    "a7": {
        "name": "Guthabenaufladeautomat (Karte)",
        "data": 1319,
        "x": 31,
        "y": 48,
        "weights": {
            "h154": 5.1
        }
    },
    "a8": {
        "name": "Guthabenaufladeautomat (Bargeld)",
        "data": 1319,
        "x": 31,
        "y": 43,
        "weights": {
            "h154": 8.1
        }
    },
    "h153": {
        "name": "Flur",
        "data": 1314,
        "x": 26,
        "y": 54,
        "weights": {
            "e6": 3.0,
            "e11": 10.0,
            "h154": 6.1,
            "h156": 13.0
        }
    },
    "e6": {
        "name": "Haupteingang",
        "data": 5413,
        "x": 26,
        "y": 57,
        "weights": {
            "h152": 3.0,
            "h153": 3.0
        }
    },
    "h152": {
        "name": "Flur",
        "data": 1314,
        "x": 26,
        "y": 60,
        "weights": {
            "e6": 3.0,
            "h151": 38.0
        }
    },
    "e11": {
        "name": "Eingang",
        "data": 5413,
        "x": 26,
        "y": 44,
        "weights": {
            "h140": 4.0,
            "h153": 10.0
        }
    },
    "h140": {
        "name": "Flur",
        "data": 1314,
        "x": 26,
        "y": 40,
        "weights": {
            "e11": 4.0,
            "e7": 3.2,
            "h141": 14.0,
            "h139": 22.0
        }
    },
    "h139": {
        "name": "Flur",
        "data": 1314,
        "x": 26,
        "y": 18,
        "weights": {
            "e8": 3.0,
            "h140": 22.0
        }
    },
    "h156": {
        "name": "Flur",
        "data": 1314,
        "x": 13,
        "y": 54,
        "weights": {
            "auf6": 2.0,
            "h153": 13.0,
            "a3": 4.4,
            "h125": 4.0
        }
    },
    "a3": {
        "name": "Thoskavalidierungsautomat",
        "data": 1319,
        "x": 17,
        "y": 52,
        "weights": {
            "h156": 4.4
        }
    },
    "auf6": {
        "name": "Aufzug",
        "data": 1316,
        "x": 11,
        "y": 54,
        "weights": {
            "auf5": 5.0,
            "h156": 2.0
        }
    },
    "h125": {
        "name": "Flur",
        "data": 1314,
        "x": 13,
        "y": 50,
        "weights": {
            "h156": 4.0,
            "h124": 9.0,
            "h126": 11.0,
            "t_basement": 2.0
        }
    },
    "h124": {
        "name": "Flur",
        "data": 1314,
        "x": 4,
        "y": 50,
        "weights": {
            "audi": 1.0,
            "gk": 3.0,
            "h125": 9.0
        }
    },
    "audi": {
        "name": "Audimax",
        "data": 1313,
        "x": 3,
        "y": 50,
        "weights": {
            "h124": 1.0
        }
    },
    "gk": {
        "name": "Grünes Klassenzimmer",
        "data": 1313,
        "x": 4,
        "y": 47,
        "weights": {
            "h124": 3.0
        }
    },
    "h126": {
        "name": "Flur",
        "data": 1314,
        "x": 13,
        "y": 39,
        "weights": {
            "h125": 11.0,
            "t16": 3.6,
            "h127": 4.0,
            "h129": 4.0,
            "et": 1.4,
            "h128": 5.0
        }
    },
    "t16": {
        "name": "Treppe",
        "data": 291,
        "x": 15,
        "y": 42,
        "weights": {
            "t11": 5.0,
            "h126": 3.6
        }
    },
    "t_basement": {
        "name": "Treppe",
        "data": 291,
        "x": 15,
        "y": 51,
        "weights": {
            "h125": 2.0
        }
    },
    "et": {
        "name": "ET-Labor",
        "data": 1313,
        "x": 12,
        "y": 38,
        "weights": {
            "h126": 1.4
        }
    },
    "b020": {
        "name": "Bür0 B20",
        "data": 1313,
        "x": 12,
        "y": 35,
        "weights": {
            "h129": 1.0
        }
    },
    "h127": {
        "name": "Flur",
        "data": 1314,
        "x": 17,
        "y": 39,
        "weights": {
            "b32": 1.0,
            "h126": 4.0,
            "h128": 3.0,
            "e7": 6.0
        }
    },
    "b32": {
        "name": "Computerraum B032",
        "data": 1313,
        "x": 17,
        "y": 40,
        "weights": {
            "h127": 1.0
        }
    },
    "e7": {
        "name": "Eingang",
        "data": 5413,
        "x": 23,
        "y": 39,
        "weights": {
            "h140": 3.1,
            "h127": 6.0
        }
    },
    "h128": {
        "name": "Flur",
        "data": 1314,
        "x": 17,
        "y": 36,
        "weights": {
            "h127": 3.0,
            "b31": 1.0,
            "h129": 4.1,
            "h126": 5.0,
            "b30": 3.0
        }
    },
    "b31": {
        "name": "Treffpunkt B031",
        "data": 1313,
        "x": 18,
        "y": 36,
        "weights": {
            "h128": 1.0
        }
    },
    "b30": {
        "name": "IT B030",
        "data": 1313,
        "x": 17,
        "y": 33,
        "weights": {
            "h128": 3.0
        }
    },
    "h129": {
        "name": "Flur",
        "data": 1314,
        "x": 13,
        "y": 35,
        "weights": {
            "b020": 1.0,
            "t15": 2.8,
            "h128": 4.1,
            "h126": 4.0,
            "h127": 5.6,
            "h130": 10.0
        }
    },
    "t15": {
        "name": "Treppe",
        "data": 291,
        "x": 15,
        "y": 33,
        "weights": {
            "t12": 5.0,
            "h129": 2.8
        }
    },
    "h130": {
        "name": "Flur",
        "data": 1314,
        "x": 13,
        "y": 25,
        "weights": {
            "at": 1.0,
            "h129": 10.0,
            "h131": 4.0
        }
    },
    "at": {
        "name": "AT-Labor",
        "data": 1313,
        "x": 12,
        "y": 25,
        "weights": {
            "h130": 1.0
        }
    },
    "cim": {
        "name": "CIM-Labor",
        "data": 1313,
        "x": 12,
        "y": 21,
        "weights": {
            "h131": 1.0
        }
    },
    "h131": {
        "name": "Flur",
        "data": 1314,
        "x": 13,
        "y": 21,
        "weights": {
            "h130": 4.0,
            "cim": 1.0,
            "h132": 4.0
        }
    },
    "b29": {
        "name": "Computerraum B029",
        "data": 1313,
        "x": 17,
        "y": 19,
        "weights": {
            "h133": 1.0
        }
    },
    "b28": {
        "name": "Internetraum B028",
        "data": 9505,
        "x": 18,
        "y": 14,
        "weights": {
            "h134": 1.0
        }
    },
    "b27": {
        "name": "Computerraum B027",
        "data": 1313,
        "x": 17,
        "y": 12,
        "weights": {
            "h134": 2.0,
            "h136": 4.0
        }
    },
    "b26": {
        "name": "Lager B026",
        "data": 9505,
        "x": 12,
        "y": 5,
        "weights": {
            "h138": 1.0
        }
    },
    "b25": {
        "name": "Hausmeister B025",
        "data": 9505,
        "x": 7,
        "y": 8,
        "weights": {
            "h137": 4.0
        }
    },
    "saal1": {
        "name": "Hörsaal",
        "data": 1313,
        "x": 0,
        "y": 12,
        "weights": {
            "h137": 7.0
        }
    },
    "saal2": {
        "name": "Hörsaal links",
        "data": 1313,
        "x": 0,
        "y": 10,
        "weights": {
            "h137": 7.3
        }
    },
    "h137": {
        "name": "Flur",
        "data": 1314,
        "x": 7,
        "y": 12,
        "weights": {
            "saal2": 7.3,
            "saal1": 7.0,
            "b25": 4.0,
            "h136": 6.0
        }
    },
    "h136": {
        "name": "Flur",
        "data": 1314,
        "x": 13,
        "y": 12,
        "weights": {
            "h137": 6.0,
            "h138": 7.0,
            "h135": 2.0,
            "b27": 4.0,
            "t14": 2.8
        }
    },
    "t14": {
        "name": "Treppe",
        "data": 291,
        "x": 15,
        "y": 10,
        "weights": {
            "h136": 2.8,
            "t13": 5.0
        }
    },
    "h138": {
        "name": "Flur",
        "data": 1314,
        "x": 13,
        "y": 5,
        "weights": {
            "b26": 1.0,
            "h136": 7.0,
            "e9": 5.0
        }
    },
    "e9": {
        "name": "Eingang",
        "data": 5413,
        "x": 13,
        "y": 0,
        "weights": {
            "h138": 5.0
        }
    },
    "e8": {
        "name": "Eingang",
        "data": 5413,
        "x": 23,
        "y": 18,
        "weights": {
            "h139": 3.0,
            "h133": 6.1
        }
    },
    "h133": {
        "name": "Flur",
        "data": 1314,
        "x": 17,
        "y": 17,
        "weights": {
            "e8": 6.1,
            "b29": 1.0,
            "h132": 4.0,
            "h134": 3.0,
            "h135": 5.0
        }
    },
    "h132": {
        "name": "Flur",
        "data": 1314,
        "x": 13,
        "y": 17,
        "weights": {
            "h131": 4.0,
            "h133": 4.0,
            "h135": 3.0,
            "h134": 5.0
        }
    },
    "h135": {
        "name": "Flur",
        "data": 1314,
        "x": 13,
        "y": 14,
        "weights": {
            "h132": 3.0,
            "h133": 5.0,
            "h134": 4.0,
            "h136": 2.0
        }
    },
    "h134": {
        "name": "Flur",
        "data": 1314,
        "x": 17,
        "y": 14,
        "weights": {
            "b28": 1.0,
            "b27": 2.0,
            "h133": 3.0,
            "h132": 5.0,
            "h135": 4.0
        }
    }
}